run_dag/__init__.py
run_dag/__main__.py
run_dag/utils/__init__.py
run_dag/utils/exceptions.py
run_dag/utils/get_dag.py
run_dag/utils/parse_settings_file.py
run_dag/utils/run_dag.py
run_dag/utils/version_compat.py
astro_run_dag-0.2.10.dist-info/METADATA
astro_run_dag-0.2.10.dist-info/WHEEL
astro_run_dag-0.2.10.dist-info/entry_points.txt
astro_run_dag-0.2.10.dist-info/RECORD
